{
	"animations": [
		{
			"offsets": [
				-68,
				72
			],
			"loop": false,
			"anim": "singRIGHTmiss",
			"fps": 24,
			"name": "Pico NOTE LEFT miss",
			"indices": []
		},
		{
			"offsets": [
				62,
				64
			],
			"loop": false,
			"anim": "singLEFTmiss",
			"fps": 24,
			"name": "Pico Note Right Miss",
			"indices": []
		},
		{
			"offsets": [
				210,
				-28
			],
			"loop": false,
			"anim": "singDOWNmiss",
			"fps": 24,
			"name": "Pico Down Note MISS",
			"indices": []
		},
		{
			"offsets": [
				-19,
				67
			],
			"loop": false,
			"anim": "singUPmiss",
			"fps": 24,
			"name": "pico Up note miss",
			"indices": []
		},
		{
			"offsets": [
				-216,
				230
			],
			"loop": false,
			"fps": 24,
			"anim": "singRIGHT",
			"indices": [],
			"name": "right"
		},
		{
			"loop": false,
			"offsets": [
				0,
				0
			],
			"anim": "",
			"fps": 24,
			"name": "",
			"indices": []
		},
		{
			"loop": false,
			"offsets": [
				-214,
				309
			],
			"anim": "singUP",
			"fps": 24,
			"name": "up",
			"indices": []
		},
		{
			"loop": false,
			"offsets": [
				-215,
				247
			],
			"anim": "idle",
			"fps": 24,
			"name": "idle",
			"indices": []
		},
		{
			"loop": false,
			"offsets": [
				-35,
				184
			],
			"anim": "singDOWN",
			"fps": 24,
			"name": "down",
			"indices": []
		},
		{
			"loop": false,
			"offsets": [
				-114,
				219
			],
			"anim": "singLEFT",
			"fps": 24,
			"name": "left",
			"indices": []
		}
	],
	"no_antialiasing": false,
	"image": "characters/DJKnifeSprites",
	"position": [
		20,
		300
	],
	"healthicon": "drawing-jeffy",
	"flip_x": false,
	"healthbar_colors": [
		255,
		195,
		0
	],
	"camera_position": [
		-100,
		-210
	],
	"sing_duration": 4,
	"scale": 1
}